docs/conf.py
pagn/Sirko.py
pagn/Thompson.py
pagn/__init__.py
pagn/__version__.py
pagn/constants.py
pagn/opacities.py
pagn/opacity_tables/logRT_combined_Raxis.dat
pagn/opacity_tables/logRT_combined_Taxis.dat
pagn/opacity_tables/logRT_combined_table.dat
pagn/opacity_tables/opacity_table.dat
utils/opacity_sources/Semenov2003/generate_combined_tables.py
utils/opacity_sources/Semenov2003/test_pysemenov.py
pagn-1.0.0.dist-info/LICENSE
pagn-1.0.0.dist-info/METADATA
pagn-1.0.0.dist-info/WHEEL
pagn-1.0.0.dist-info/top_level.txt
pagn-1.0.0.dist-info/RECORD
