Metadata-Version: 2.1
Name: pagn
Version: 1.0.0
Summary: Solutions to parametric AGN disk models
Author-email: Daria Gangardt <ddg672@student.bham.ac.uk>, "Alessandro A. Trani" <aatrani@gmail.com>
License: GNU GENERAL PUBLIC LICENSE
Project-URL: Documentation, https://dariagangardt.github.io/pagn/
Project-URL: Repository, https://github.com/DariaGangardt/pagn
License-File: LICENSE
Requires-Dist: numpy
Requires-Dist: scipy >=1.10.0
Requires-Dist: matplotlib
